geosample/__init__.py
geosample/cli.py
geosample/geosample.py
geosample-0.3.0.dist-info/DESCRIPTION.rst
geosample-0.3.0.dist-info/METADATA
geosample-0.3.0.dist-info/RECORD
geosample-0.3.0.dist-info/WHEEL
geosample-0.3.0.dist-info/entry_points.txt
geosample-0.3.0.dist-info/metadata.json
geosample-0.3.0.dist-info/top_level.txt
