Metadata-Version: 2.0
Name: geosample
Version: 0.3.0
Summary: Sample locations from geospatial inputs
Home-page: https://github.com/jo-tham/geosample
Author: Jotham Apaloo
Author-email: jothamapaloo@gmail.com
License: Apache Software License 2.0
Keywords: geosample
Platform: UNKNOWN
Classifier: Development Status :: 2 - Pre-Alpha
Classifier: Intended Audience :: Developers
Classifier: License :: OSI Approved :: Apache Software License
Classifier: Natural Language :: English
Classifier: Programming Language :: Python :: 2
Classifier: Programming Language :: Python :: 2.6
Classifier: Programming Language :: Python :: 2.7
Classifier: Programming Language :: Python :: 3
Classifier: Programming Language :: Python :: 3.3
Classifier: Programming Language :: Python :: 3.4
Classifier: Programming Language :: Python :: 3.5
Requires-Dist: Click (>=6.0)
Requires-Dist: geojson (>=1.3.3)
Requires-Dist: shapely (>=1.5.17)
Requires-Dist: typing (>=3.5.3.0)
